pushbullet_api/PushbulletAPI.py
pushbullet_api/__init__.py
pushbullet_api-0.1.1.dist-info/METADATA
pushbullet_api-0.1.1.dist-info/WHEEL
pushbullet_api-0.1.1.dist-info/top_level.txt
pushbullet_api-0.1.1.dist-info/RECORD
